<?xml version='1.0' encoding='UTF-8'?>
<!DOCTYPE markables SYSTEM "markables.dtd">
<markables xmlns="www.eml.org/NameSpaces/action">
  <markable id="markable_0" mmax_level="action" order_id="0" span="word_25" imageview="images/B4-A19-C8-1522882559576_4.png" world_state="s1"/>
  <markable id="markable_1" mmax_level="action" order_id="1" span="word_26" imageview="images/B4-A19-C8-1522882559576_5.png" world_state="s2"/>
  <markable id="markable_2" mmax_level="action" order_id="2" span="word_27" imageview="images/B4-A19-C8-1522882559576_6.png" world_state="s3"/>
  <markable id="markable_3" mmax_level="action" order_id="3" span="word_41" imageview="images/B4-A19-C8-1522882559576_7.png" world_state="s4"/>
  <markable id="markable_4" mmax_level="action" order_id="4" span="word_42" imageview="images/B4-A19-C8-1522882559576_9.png" world_state="s5"/>
  <markable id="markable_5" mmax_level="action" order_id="5" span="word_47" imageview="images/B4-A19-C8-1522882559576_10.png" world_state="s6"/>
  <markable id="markable_6" mmax_level="action" order_id="6" span="word_48" imageview="images/B4-A19-C8-1522882559576_12.png" world_state="s7"/>
  <markable id="markable_7" mmax_level="action" order_id="7" span="word_49" imageview="images/B4-A19-C8-1522882559576_13.png" world_state="s8"/>
  <markable id="markable_8" mmax_level="action" order_id="8" span="word_50" imageview="images/B4-A19-C8-1522882559576_14.png" world_state="s9"/>
  <markable id="markable_9" mmax_level="action" order_id="9" span="word_51" imageview="images/B4-A19-C8-1522882559576_15.png" world_state="s10"/>
  <markable id="markable_10" mmax_level="action" order_id="10" span="word_52" imageview="images/B4-A19-C8-1522882559576_16.png" world_state="s11"/>
  <markable id="markable_11" mmax_level="action" order_id="11" span="word_57" imageview="images/B4-A19-C8-1522882559576_17.png" world_state="s12"/>
</markables>
